AUTHORS.md
CONTRIBUTING.md
HISTORY.md
LICENSE
MANIFEST.in
README.md
setup.cfg
setup.py
docs/Makefile
docs/conf.py
docs/make.bat
opendc_eemm/__init__.py
opendc_eemm/__main__.py
opendc_eemm/decision.py
opendc_eemm/market.py
opendc_eemm/preprocess.py
opendc_eemm/visualization.py
opendc_eemm.egg-info/PKG-INFO
opendc_eemm.egg-info/SOURCES.txt
opendc_eemm.egg-info/dependency_links.txt
opendc_eemm.egg-info/entry_points.txt
opendc_eemm.egg-info/not-zip-safe
opendc_eemm.egg-info/requires.txt
opendc_eemm.egg-info/top_level.txt
tests/__init__.py
tests/opendc_eemm_test.py