Metadata-Version: 2.1
Name: opendc-eemm
Version: 0.0.3
Summary: ''
Home-page: https://github.com/hongyuhe/opendc-eemm
Author: Hongyu He
Author-email: hongyuhe.cs@googlemail.com
License: Apache Software License 2.0
Keywords: opendc-eemm
Platform: UNKNOWN
Classifier: Development Status :: 2 - Pre-Alpha
Classifier: Intended Audience :: Developers
Classifier: License :: OSI Approved :: Apache Software License
Classifier: Natural Language :: English
Classifier: Programming Language :: Python :: 3
Classifier: Programming Language :: Python :: 3.6
Classifier: Programming Language :: Python :: 3.7
Classifier: Programming Language :: Python :: 3.8
Requires-Python: >=3.6
